fhub
